{"cameraMode":{"drawMode":0,"name":"Shaded","section":"Shading Mode"},"sceneLighting":true,"audioPlay":false,"sceneViewState":{"m_AlwaysRefresh":false,"showFog":true,"showSkybox":true,"showFlares":true,"showImageEffects":true,"showParticleSystems":true,"showVisualEffectGraphs":true,"m_FxEnabled":true},"in2DMode":false,"pivot":{"x":3.804377555847168,"y":0.6342054009437561,"z":1.342087745666504},"rotation":{"x":-0.1450461745262146,"y":-0.6812207102775574,"z":0.14062198996543885,"w":-0.7037904858589172},"size":4.632835865020752,"orthographic":false}